flask_hashing.py
Flask_Hashing-1.0.dist-info/WHEEL
Flask_Hashing-1.0.dist-info/top_level.txt
Flask_Hashing-1.0.dist-info/RECORD
Flask_Hashing-1.0.dist-info/DESCRIPTION.rst
Flask_Hashing-1.0.dist-info/metadata.json
Flask_Hashing-1.0.dist-info/METADATA
