Metadata-Version: 2.0
Name: Flask-Hashing
Version: 1.0
Summary: Easy hashing of data in Flask
Home-page: https://github.com/ThaWeatherman/flask-hashing
Author: Sean Beck
Author-email: seanmckaybeck@gmail.com
License: MIT
Platform: any
Classifier: Environment :: Web Environment
Classifier: Intended Audience :: Developers
Classifier: License :: OSI Approved :: MIT License
Classifier: Operating System :: OS Independent
Classifier: Programming Language :: Python
Classifier: Topic :: Internet :: WWW/HTTP :: Dynamic Content
Classifier: Topic :: Software Development :: Libraries :: Python Modules
Requires-Dist: Flask
